b2luigi/__init__.py
b2luigi/basf2_helper/__init__.py
b2luigi/basf2_helper/targets.py
b2luigi/basf2_helper/tasks.py
b2luigi/basf2_helper/utils.py
b2luigi/batch/__init__.py
b2luigi/batch/cache.py
b2luigi/batch/workers.py
b2luigi/batch/processes/__init__.py
b2luigi/batch/processes/apptainer.py
b2luigi/batch/processes/gbasf2.py
b2luigi/batch/processes/htcondor.py
b2luigi/batch/processes/lsf.py
b2luigi/batch/processes/slurm.py
b2luigi/batch/processes/test.py
b2luigi/batch/processes/gbasf2_utils/gbasf2_download_utils.py
b2luigi/batch/processes/gbasf2_utils/gbasf2_ds_list.py
b2luigi/batch/processes/gbasf2_utils/gbasf2_job_status.py
b2luigi/batch/processes/gbasf2_utils/gbasf2_proxy_info.py
b2luigi/batch/processes/gbasf2_utils/pickle_utils.py
b2luigi/batch/processes/templates/gbasf2_steering_file_wrapper.jinja2
b2luigi/cli/__init__.py
b2luigi/cli/arguments.py
b2luigi/cli/process.py
b2luigi/cli/runner.py
b2luigi/core/__init__.py
b2luigi/core/dispatchable_task.py
b2luigi/core/executable.py
b2luigi/core/parameter.py
b2luigi/core/settings.py
b2luigi/core/target.py
b2luigi/core/task.py
b2luigi/core/temporary_wrapper.py
b2luigi/core/utils.py
b2luigi/core/xrootd_targets.py
b2luigi-1.2.7.dist-info/licenses/LICENSE
b2luigi-1.2.7.dist-info/WHEEL
b2luigi-1.2.7.dist-info/METADATA
b2luigi-1.2.7.dist-info/RECORD
